LICENSE
MANIFEST.in
README.md
VERSION
setup.cfg
setup.py
tox.ini
docs/api.rst
docs/conf.py
docs/development.rst
docs/index.rst
docs/install.rst
docs/manual.rst
docs/manual_advanced.rst
docs/manual_arguments.rst
docs/manual_basic.rst
docs/manual_defaults.rst
docs/manual_grouping.rst
docs/manual_options.rst
docs/manual_subcommands.rst
docs/tutorial.rst
docs/.themes/subcmd/body.html
docs/.themes/subcmd/domainindex.html
docs/.themes/subcmd/genindex.html
docs/.themes/subcmd/layout.html
docs/.themes/subcmd/page.html
docs/.themes/subcmd/search.html
docs/.themes/subcmd/static/bootstrap.css
docs/.themes/subcmd/static/bootstrap.js
docs/.themes/subcmd/static/doctools.js
docs/.themes/subcmd/static/glyphicons-halflings-white.png
docs/.themes/subcmd/static/glyphicons-halflings.png
docs/.themes/subcmd/static/jquery.js
docs/.themes/subcmd/static/pygments.css
docs/.themes/subcmd/static/subcmd.css
docs/.themes/subcmd/static/subcmd.js
docs/.themes/subcmd/static/underscore.js
subcmd/__init__.py
subcmd/app.py
subcmd/base.py
subcmd/decorators.py
subcmd.egg-info/PKG-INFO
subcmd.egg-info/SOURCES.txt
subcmd.egg-info/dependency_links.txt
subcmd.egg-info/namespace_packages.txt
subcmd.egg-info/not-zip-safe
subcmd.egg-info/top_level.txt
tests/context.py
tests/test_basic.py
tests/test_builder.py
tests/test_inherited.py