Metadata-Version: 1.1
Name: subcmd
Version: 0.3
Summary: A Python module that implements subcommands CLI pattern.
Home-page: https://github.com/repejota/subcmd
Author: Raul Perez
Author-email: repejota@gmail.com
License: #
